CHANGES
LICENSE
MANIFEST.in
README.rst
setup.cfg
setup.py
zorker/__init__.py
zorker/dfrotz.py
zorker.egg-info/PKG-INFO
zorker.egg-info/SOURCES.txt
zorker.egg-info/dependency_links.txt
zorker.egg-info/entry_points.txt
zorker.egg-info/not-zip-safe
zorker.egg-info/requires.txt
zorker.egg-info/top_level.txt
zorker/tests/__init__.py