Metadata-Version: 1.1
Name: zorker
Version: 0.1
Summary: A Twitter bot to play text adventure games
Home-page: http://github.com/storborg/zorker
Author: Scott Torborg
Author-email: storborg@gmail.com
License: MIT
Keywords: zork infocom text adventure twitter bot
Platform: UNKNOWN
Classifier: Development Status :: 3 - Alpha
Classifier: License :: OSI Approved :: MIT License
Classifier: Programming Language :: Python :: 2
Classifier: Programming Language :: Python :: 2.7
Classifier: Topic :: Internet :: WWW/HTTP
